tevec/__init__.py
tevec-0.0.1rc4.dist-info/METADATA
tevec-0.0.1rc4.dist-info/WHEEL
tevec-0.0.1rc4.dist-info/RECORD
