Metadata-Version: 2.1
Name: tevec
Version: 0.0.1rc4
Summary: 
Author: Nick Badger
Author-email: nbadger1@gmail.com
Requires-Python: >=3.12
Classifier: Programming Language :: Python :: 3
Classifier: Programming Language :: Python :: 3.12
